olyptik/__init__.py
olyptik/client.py
olyptik/errors.py
olyptik/models.py
olyptik/py.typed
olyptik-0.1.6.dist-info/licenses/LICENSE
olyptik-0.1.6.dist-info/METADATA
olyptik-0.1.6.dist-info/WHEEL
olyptik-0.1.6.dist-info/top_level.txt
olyptik-0.1.6.dist-info/RECORD
