Metadata-Version: 2.4
Name: olyptik
Version: 0.1.6
Summary: Official Python SDK for Olyptik API
Author-email: Olyptik <support@olyptik.io>
License: MIT
Project-URL: Homepage, https://olyptik.io
Keywords: sdk,crawler,olyptik,api
Classifier: Programming Language :: Python :: 3
Classifier: Programming Language :: Python :: 3 :: Only
Classifier: License :: OSI Approved :: MIT License
Classifier: Operating System :: OS Independent
Classifier: Typing :: Typed
Requires-Python: >=3.8
License-File: LICENSE
Requires-Dist: httpx>=0.27.0
Requires-Dist: python-dotenv>=1.0.1
Requires-Dist: typing-extensions>=4.8.0
Dynamic: license-file
